README.md
setup.py
labs/__init__.py
labs/base.py
labs/experimenting.py
labs/lab.py
labs/lab_utils.py
labs/reporting.py
labs/searchers.py
labs/wrappers.py
labs.egg-info/PKG-INFO
labs.egg-info/SOURCES.txt
labs.egg-info/dependency_links.txt
labs.egg-info/requires.txt
labs.egg-info/top_level.txt