Metadata-Version: 2.1
Name: labs
Version: 0.0.4
Summary: labs - a dask-distributed experiments manager
Home-page: https://github.com/Brillone/labs
Author: Eran Brill
Author-email: brillonedev@gmail.com
License: UNKNOWN
Download-URL: https://github.com/Brillone/labs/archive/v0.0.4.tar.gz
Platform: UNKNOWN
Classifier: Programming Language :: Python :: 3
Classifier: License :: OSI Approved :: MIT License
Classifier: Operating System :: OS Independent
Requires-Python: >=3.6
